envantage/__init__.py
envantage-0.0.0.dist-info/LICENSE
envantage-0.0.0.dist-info/WHEEL
envantage-0.0.0.dist-info/METADATA
envantage-0.0.0.dist-info/RECORD
